README.md
setup.py
Pro_Pacote/__init__.py
Pro_Pacote/camera.py
Pro_Pacote/video.py
hugo_paulo_project.egg-info/PKG-INFO
hugo_paulo_project.egg-info/SOURCES.txt
hugo_paulo_project.egg-info/dependency_links.txt
hugo_paulo_project.egg-info/top_level.txt