Metadata-Version: 1.0
Name: hugo-paulo-project
Version: 1.0
Summary: Este pacote ira fornecer ferramentas de processamento de video
Home-page: UNKNOWN
Author: Hugo
Author-email: hugo@gmail.com
License: UNKNOWN
Keywords: camera,video,processamento
Platform: UNKNOWN
